phronesitron/__init__.py
phronesitron/executables.py
phronesitron-0.1.8.dist-info/LICENSE
phronesitron-0.1.8.dist-info/WHEEL
phronesitron-0.1.8.dist-info/entry_points.txt
phronesitron-0.1.8.dist-info/METADATA
phronesitron-0.1.8.dist-info/RECORD
